datatoolbox/__init__.py
datatoolbox/admin.py
datatoolbox/config.py
datatoolbox/converters.py
datatoolbox/core.py
datatoolbox/data_structures.py
datatoolbox/database.py
datatoolbox/indexing.py
datatoolbox/init_tools.py
datatoolbox/interfaces.py
datatoolbox/mapping.py
datatoolbox/naming_convention.py
datatoolbox/patches.py
datatoolbox/pint_definitions.txt
datatoolbox/sets.py
datatoolbox/unit_registry.py
datatoolbox/util.py
datatoolbox/version.py
datatoolbox/visualissation_analysis.py
datatoolbox/data/GHG_alternative_naming.pkl
datatoolbox/data/GHG_properties_2019_CA.csv
datatoolbox/data/all.csv
datatoolbox/data/compatible1_5_unfiltered.xlsx
datatoolbox/data/continent.csv
datatoolbox/data/country_codes.csv
datatoolbox/data/datashelf_contents.csv
datatoolbox/data/external_mappings.py
datatoolbox/data/personal_template.py
datatoolbox/data/regions.csv
datatoolbox/data/SANDBOX_datashelf/inventory.csv
datatoolbox/data/SANDBOX_datashelf/sources.csv
datatoolbox/data/SANDBOX_datashelf/mappings/continent.csv
datatoolbox/data/SANDBOX_datashelf/mappings/country_codes.csv
datatoolbox/data/SANDBOX_datashelf/mappings/regions.csv
datatoolbox/tools/CRF_extract_CA_2021.xlsx
datatoolbox/tools/EQW_SPLIT_EFF0460_CATEFFEXT_210120.SCEN
datatoolbox/tools/IEA_B2DS_4.SCEN
datatoolbox/tools/WEO_2019_test.SCEN
datatoolbox/tools/__init__.py
datatoolbox/tools/conversion_to_v0.3.py
datatoolbox/tools/export_all.py
datatoolbox/tools/for_datatables.py
datatoolbox/tools/html.py
datatoolbox/tools/install_support.py
datatoolbox/tools/new_SR15_pathway_matching.py
datatoolbox/tools/pandas.py
datatoolbox/tools/pyam.py
datatoolbox/tools/run_MAGICC_startup_simple.xlsx
datatoolbox/tools/statistics.py
datatoolbox/tools/test.docx
datatoolbox/tools/word.py
datatoolbox/tools/xarray.py
datatoolbox/tutorials/00_search_find_and_access_data.py
datatoolbox/tutorials/01_emission_comparison.py
datatoolbox/tutorials/02_unit_conversion.py
datatoolbox/tutorials/03_intermediate_example.py
datatoolbox/tutorials/04_sources.py
datatoolbox-0.9.2.dist-info/LICENSE
datatoolbox-0.9.2.dist-info/METADATA
datatoolbox-0.9.2.dist-info/WHEEL
datatoolbox-0.9.2.dist-info/top_level.txt
datatoolbox-0.9.2.dist-info/RECORD
