Metadata-Version: 2.1
Name: datatoolbox
Version: 0.9.2
Summary: The Python Data Toolbox
Home-page: https://gitlab.com/climateanalytics/datatoolbox
Author: Andreas Geiges
Author-email: a.geiges@gmail.com
License-File: LICENSE
Requires-Dist: appdirs
Requires-Dist: pandas
Requires-Dist: gitpython
Requires-Dist: openscm-units
Requires-Dist: pint
Requires-Dist: pint-xarray
Requires-Dist: pycountry
Requires-Dist: fuzzywuzzy
Requires-Dist: tqdm
Requires-Dist: pyam-iamc
Requires-Dist: pyarrow
Requires-Dist: networkx
Requires-Dist: openpyxl
Requires-Dist: tabulate
Requires-Dist: xarray
Requires-Dist: deprecated
Requires-Dist: treelib
Requires-Dist: xlsxwriter
